models/__init__.py
models/models.py
paybidelec/__init__.py
paybidelec/models.py
paybidelec-0.3.1.dist-info/METADATA
paybidelec-0.3.1.dist-info/RECORD
paybidelec-0.3.1.dist-info/WHEEL
paybidelec-0.3.1.dist-info/top_level.txt
