Metadata-Version: 2.1
Name: paybidelec
Version: 0.3.1
Summary: pay as a bid for electricity auction model
Home-page: UNKNOWN
Author: Amirhosein Shirani
Author-email: amirhhh.shirani@yahoo.com
License: Shatif University of Technology
Platform: UNKNOWN
